fds/__init__.py
fds/sdk/__init__.py
fds/sdk/FactSetESG/__init__.py
fds/sdk/FactSetESG/api_client.py
fds/sdk/FactSetESG/configuration.py
fds/sdk/FactSetESG/exceptions.py
fds/sdk/FactSetESG/model_utils.py
fds/sdk/FactSetESG/rest.py
fds/sdk/FactSetESG/api/__init__.py
fds/sdk/FactSetESG/api/articles_api.py
fds/sdk/FactSetESG/api/sasb_api.py
fds/sdk/FactSetESG/api/spotlights_api.py
fds/sdk/FactSetESG/apis/__init__.py
fds/sdk/FactSetESG/model/__init__.py
fds/sdk/FactSetESG/model/articles_fields.py
fds/sdk/FactSetESG/model/calendar.py
fds/sdk/FactSetESG/model/categories.py
fds/sdk/FactSetESG/model/date_of.py
fds/sdk/FactSetESG/model/error_response.py
fds/sdk/FactSetESG/model/error_response_sub_errors.py
fds/sdk/FactSetESG/model/fields_sasb_spotlights.py
fds/sdk/FactSetESG/model/frequency.py
fds/sdk/FactSetESG/model/ids.py
fds/sdk/FactSetESG/model/pai_ids.py
fds/sdk/FactSetESG/model/rank_categories.py
fds/sdk/FactSetESG/model/sasb_article.py
fds/sdk/FactSetESG/model/sasb_articles_categories.py
fds/sdk/FactSetESG/model/sasb_articles_request.py
fds/sdk/FactSetESG/model/sasb_articles_response.py
fds/sdk/FactSetESG/model/sasb_ranks.py
fds/sdk/FactSetESG/model/sasb_ranks_request.py
fds/sdk/FactSetESG/model/sasb_ranks_response.py
fds/sdk/FactSetESG/model/sasb_score_types.py
fds/sdk/FactSetESG/model/sasb_scores.py
fds/sdk/FactSetESG/model/sasb_scores_all.py
fds/sdk/FactSetESG/model/sasb_scores_all_request.py
fds/sdk/FactSetESG/model/sasb_scores_all_response.py
fds/sdk/FactSetESG/model/sasb_scores_request.py
fds/sdk/FactSetESG/model/sasb_scores_response.py
fds/sdk/FactSetESG/model/sasb_spotlights_categories.py
fds/sdk/FactSetESG/model/sasb_spotlights_request.py
fds/sdk/FactSetESG/model/spotlights.py
fds/sdk/FactSetESG/model/spotlights_response.py
fds/sdk/FactSetESG/models/__init__.py
fds.sdk.FactSetESG-1.3.6.dist-info/LICENSE
fds.sdk.FactSetESG-1.3.6.dist-info/METADATA
fds.sdk.FactSetESG-1.3.6.dist-info/WHEEL
fds.sdk.FactSetESG-1.3.6.dist-info/top_level.txt
fds.sdk.FactSetESG-1.3.6.dist-info/RECORD
